srai_langchain/__init__.py
srai_langchain/client_pubmed.py
srai_langchain/rag/__init__.py
srai_langchain/rag/cbm_store.py
srai_langchain/rag/rag_agent.py
srai_langchain/rag/rag_agent_store.py
srai_langchain/rag/source_store.py
srai_langchain/rag/vectorstore_store.py
srai_langchain/tools_langchain.py
srai_langchain-0.1.0.dist-info/LICENSE
srai_langchain-0.1.0.dist-info/METADATA
srai_langchain-0.1.0.dist-info/WHEEL
srai_langchain-0.1.0.dist-info/RECORD
